sdmenu/__init__.py
sdmenu/classes.py
sdmenu/parser.py
sdmenu/webworker.py
sdmenu-1.0.0.dist-info/LICENSE
sdmenu-1.0.0.dist-info/METADATA
sdmenu-1.0.0.dist-info/WHEEL
sdmenu-1.0.0.dist-info/top_level.txt
sdmenu-1.0.0.dist-info/RECORD
