Metadata-Version: 2.1
Name: sdmenu
Version: 1.0.0
Summary: A simple way to query UC San Diego's HDH dining halls
Home-page: https://sdmenu.online
Author: Gideon Tong
Author-email: gideon@gideontong.com
License: UNKNOWN
Project-URL: Source, https://github.com/gideontong/sdmenu/
Project-URL: Tracker, https://github.com/gideontong/sdmenu/issues
Platform: UNKNOWN
Classifier: Development Status :: 4 - Beta
Classifier: Environment :: Web Environment
Classifier: Intended Audience :: Developers
Classifier: License :: OSI Approved :: MIT License
Classifier: Natural Language :: English
Classifier: Operating System :: OS Independent
Classifier: Programming Language :: Python :: 3.7
Classifier: Programming Language :: Python :: 3.8
Classifier: Programming Language :: Python :: 3.9
Classifier: Topic :: Internet :: WWW/HTTP :: Indexing/Search
Classifier: Topic :: Text Processing :: Indexing
Requires-Python: >=3.7.*
Requires-Dist: beautifulsoup4 (<5,>=4.9.3)
Requires-Dist: requests (<3,>=2.25.1)
